{
  "generated_at": "2026-04-08T06:55:15+02:00",
  "routes": [
    {
      "train_name": "R11",
      "train_type": "Otros",
      "total": 59,
      "delayed": 1,
      "cancelled": 0,
      "delayed_pct": 0.0169,
      "avg_delay_min": 7.0,
      "max_delay_min": 7.0,
      "arrivals": [
        {
          "train_name": "R11",
          "headsign": "Portbou",
          "origin": "Barcelona-Sants",
          "stop_id": "79104",
          "stop_name": "Sant Celoni",
          "scheduled_time": "07:03",
          "estimated_time": "07:10",
          "delay_min": 7.0,
          "status": "retraso_leve"
        }
      ]
    },
    {
      "train_name": "C10",
      "train_type": "Cercanías",
      "total": 143,
      "delayed": 0,
      "cancelled": 0,
      "delayed_pct": 0.0,
      "avg_delay_min": 1.0,
      "max_delay_min": 1.0,
      "arrivals": [
        {
          "train_name": "C10",
          "headsign": "Pinar De Las Rozas",
          "origin": "Madrid-Chamartín-Clara Campoamor",
          "stop_id": "18001",
          "stop_name": "Madrid-Recoletos",
          "scheduled_time": "06:56",
          "estimated_time": "06:57",
          "delay_min": 1.0,
          "status": "en_hora"
        }
      ]
    },
    {
      "train_name": "C8a",
      "train_type": "Cercanías",
      "total": 41,
      "delayed": 0,
      "cancelled": 0,
      "delayed_pct": 0.0,
      "avg_delay_min": 0.0,
      "max_delay_min": 0.0,
      "arrivals": []
    },
    {
      "train_name": "C8b",
      "train_type": "Cercanías",
      "total": 40,
      "delayed": 0,
      "cancelled": 0,
      "delayed_pct": 0.0,
      "avg_delay_min": 0.0,
      "max_delay_min": 0.0,
      "arrivals": []
    },
    {
      "train_name": "C7",
      "train_type": "Cercanías",
      "total": 161,
      "delayed": 0,
      "cancelled": 0,
      "delayed_pct": 0.0,
      "avg_delay_min": 0.0,
      "max_delay_min": 0.0,
      "arrivals": []
    },
    {
      "train_name": "C5",
      "train_type": "Cercanías",
      "total": 609,
      "delayed": 0,
      "cancelled": 0,
      "delayed_pct": 0.0,
      "avg_delay_min": 1.7,
      "max_delay_min": 3.0,
      "arrivals": [
        {
          "train_name": "C5",
          "headsign": "Fuenlabrada",
          "origin": "Móstoles-El Soto",
          "stop_id": "35609",
          "stop_name": "Embajadores",
          "scheduled_time": "06:56",
          "estimated_time": "06:59",
          "delay_min": 3.0,
          "status": "en_hora"
        },
        {
          "train_name": "C5",
          "headsign": "Fuenlabrada",
          "origin": "Móstoles-El Soto",
          "stop_id": "35702",
          "stop_name": "Doce De Octubre",
          "scheduled_time": "06:56",
          "estimated_time": "06:57",
          "delay_min": 1.0,
          "status": "en_hora"
        },
        {
          "train_name": "C5",
          "headsign": "Fuenlabrada",
          "origin": "Móstoles-El Soto",
          "stop_id": "35011",
          "stop_name": "Parque Polvoranca",
          "scheduled_time": "06:56",
          "estimated_time": "06:57",
          "delay_min": 1.0,
          "status": "en_hora"
        }
      ]
    },
    {
      "train_name": "C4b",
      "train_type": "Cercanías",
      "total": 146,
      "delayed": 0,
      "cancelled": 0,
      "delayed_pct": 0.0,
      "avg_delay_min": 1.0,
      "max_delay_min": 1.0,
      "arrivals": [
        {
          "train_name": "C4b",
          "headsign": "Parla",
          "origin": "Colmenar Viejo",
          "stop_id": "17004",
          "stop_name": "Tres Cantos",
          "scheduled_time": "06:59",
          "estimated_time": "07:00",
          "delay_min": 1.0,
          "status": "en_hora"
        }
      ]
    },
    {
      "train_name": "C4a",
      "train_type": "Cercanías",
      "total": 148,
      "delayed": 0,
      "cancelled": 0,
      "delayed_pct": 0.0,
      "avg_delay_min": 5.0,
      "max_delay_min": 5.0,
      "arrivals": [
        {
          "train_name": "C4a",
          "headsign": "Parla",
          "origin": "Alcobendas-San Sebastián De Los Reyes",
          "stop_id": "18002",
          "stop_name": "Madrid-Nuevos Ministerios",
          "scheduled_time": "06:56",
          "estimated_time": "07:01",
          "delay_min": 5.0,
          "status": "en_hora"
        }
      ]
    },
    {
      "train_name": "C2",
      "train_type": "Cercanías",
      "total": 438,
      "delayed": 0,
      "cancelled": 0,
      "delayed_pct": 0.0,
      "avg_delay_min": 3.0,
      "max_delay_min": 5.0,
      "arrivals": [
        {
          "train_name": "C2",
          "headsign": "Guadalajara",
          "origin": "Madrid-Nuevos Ministerios",
          "stop_id": "70200",
          "stop_name": "Guadalajara",
          "scheduled_time": "06:56",
          "estimated_time": "07:01",
          "delay_min": 5.0,
          "status": "en_hora"
        },
        {
          "train_name": "C2",
          "headsign": "Guadalajara",
          "origin": "Madrid-Chamartín-Clara Campoamor",
          "stop_id": "70200",
          "stop_name": "Guadalajara",
          "scheduled_time": "07:01",
          "estimated_time": "07:05",
          "delay_min": 4.0,
          "status": "en_hora"
        },
        {
          "train_name": "C2",
          "headsign": "Madrid-Chamartín-Clara Campoamor",
          "origin": "Guadalajara",
          "stop_id": "18000",
          "stop_name": "Madrid-Atocha Cercanías",
          "scheduled_time": "06:58",
          "estimated_time": "07:00",
          "delay_min": 2.0,
          "status": "en_hora"
        },
        {
          "train_name": "C2",
          "headsign": "L'alcúdia De Crespins",
          "origin": "València-Estació Del Nord",
          "stop_id": "64102",
          "stop_name": "La Pobla Llarga",
          "scheduled_time": "06:56",
          "estimated_time": "06:58",
          "delay_min": 2.0,
          "status": "en_hora"
        },
        {
          "train_name": "C2",
          "headsign": "Muskiz",
          "origin": "Bilbao-Intermod. Abando Indalecio Prieto",
          "stop_id": "13501",
          "stop_name": "Galindo",
          "scheduled_time": "06:57",
          "estimated_time": "06:59",
          "delay_min": 2.0,
          "status": "en_hora"
        }
      ]
    },
    {
      "train_name": "C3",
      "train_type": "Cercanías",
      "total": 385,
      "delayed": 0,
      "cancelled": 0,
      "delayed_pct": 0.0,
      "avg_delay_min": 2.0,
      "max_delay_min": 2.0,
      "arrivals": [
        {
          "train_name": "C3",
          "headsign": "Bilbao-Intermod. Abando Indalecio Prieto",
          "origin": "Orduña",
          "stop_id": "13106",
          "stop_name": "Llodio",
          "scheduled_time": "06:56",
          "estimated_time": "06:58",
          "delay_min": 2.0,
          "status": "en_hora"
        }
      ]
    },
    {
      "train_name": "C1",
      "train_type": "Cercanías",
      "total": 803,
      "delayed": 0,
      "cancelled": 0,
      "delayed_pct": 0.0,
      "avg_delay_min": 2.5,
      "max_delay_min": 3.0,
      "arrivals": [
        {
          "train_name": "C1",
          "headsign": "Madrid-Chamartín-Clara Campoamor",
          "origin": "Madrid-Aeropuerto T4",
          "stop_id": "17000",
          "stop_name": "Madrid-Chamartín-Clara Campoamor",
          "scheduled_time": "06:57",
          "estimated_time": "07:00",
          "delay_min": 3.0,
          "status": "en_hora"
        },
        {
          "train_name": "C1",
          "headsign": "Santander",
          "origin": "Renedo",
          "stop_id": "14220",
          "stop_name": "Maliaño",
          "scheduled_time": "06:56",
          "estimated_time": "06:58",
          "delay_min": 2.0,
          "status": "en_hora"
        }
      ]
    },
    {
      "train_name": "C4",
      "train_type": "Cercanías",
      "total": 191,
      "delayed": 0,
      "cancelled": 0,
      "delayed_pct": 0.0,
      "avg_delay_min": 0.0,
      "max_delay_min": 0.0,
      "arrivals": []
    },
    {
      "train_name": "C8",
      "train_type": "Cercanías",
      "total": 29,
      "delayed": 0,
      "cancelled": 0,
      "delayed_pct": 0.0,
      "avg_delay_min": 0.0,
      "max_delay_min": 0.0,
      "arrivals": []
    },
    {
      "train_name": "C6",
      "train_type": "Cercanías",
      "total": 154,
      "delayed": 0,
      "cancelled": 0,
      "delayed_pct": 0.0,
      "avg_delay_min": 0.0,
      "max_delay_min": 0.0,
      "arrivals": []
    },
    {
      "train_name": "C5a",
      "train_type": "Cercanías",
      "total": 9,
      "delayed": 0,
      "cancelled": 0,
      "delayed_pct": 0.0,
      "avg_delay_min": 0.0,
      "max_delay_min": 0.0,
      "arrivals": []
    },
    {
      "train_name": "T1",
      "train_type": "Otros",
      "total": 80,
      "delayed": 0,
      "cancelled": 0,
      "delayed_pct": 0.0,
      "avg_delay_min": 0.0,
      "max_delay_min": 0.0,
      "arrivals": []
    },
    {
      "train_name": "BUS",
      "train_type": "Otros",
      "total": 11,
      "delayed": 0,
      "cancelled": 0,
      "delayed_pct": 0.0,
      "avg_delay_min": 0.0,
      "max_delay_min": 0.0,
      "arrivals": []
    },
    {
      "train_name": "R4",
      "train_type": "Otros",
      "total": 234,
      "delayed": 0,
      "cancelled": 0,
      "delayed_pct": 0.0,
      "avg_delay_min": 0.0,
      "max_delay_min": 0.0,
      "arrivals": []
    },
    {
      "train_name": "R2S",
      "train_type": "Otros",
      "total": 111,
      "delayed": 0,
      "cancelled": 0,
      "delayed_pct": 0.0,
      "avg_delay_min": 4.0,
      "max_delay_min": 4.0,
      "arrivals": [
        {
          "train_name": "R2S",
          "headsign": "Barcelona Estació De França",
          "origin": "Sant Vicenç De Calders",
          "stop_id": "71701",
          "stop_name": "Sitges",
          "scheduled_time": "06:57",
          "estimated_time": "07:01",
          "delay_min": 4.0,
          "status": "en_hora"
        }
      ]
    },
    {
      "train_name": "R13",
      "train_type": "Otros",
      "total": 2,
      "delayed": 0,
      "cancelled": 0,
      "delayed_pct": 0.0,
      "avg_delay_min": 0.0,
      "max_delay_min": 0.0,
      "arrivals": []
    },
    {
      "train_name": "R15",
      "train_type": "Otros",
      "total": 10,
      "delayed": 0,
      "cancelled": 0,
      "delayed_pct": 0.0,
      "avg_delay_min": 0.0,
      "max_delay_min": 0.0,
      "arrivals": []
    },
    {
      "train_name": "R16",
      "train_type": "Otros",
      "total": 17,
      "delayed": 0,
      "cancelled": 0,
      "delayed_pct": 0.0,
      "avg_delay_min": 0.0,
      "max_delay_min": 0.0,
      "arrivals": []
    },
    {
      "train_name": "R14",
      "train_type": "Otros",
      "total": 15,
      "delayed": 0,
      "cancelled": 0,
      "delayed_pct": 0.0,
      "avg_delay_min": 0.0,
      "max_delay_min": 0.0,
      "arrivals": []
    },
    {
      "train_name": "RT2",
      "train_type": "Otros",
      "total": 5,
      "delayed": 0,
      "cancelled": 0,
      "delayed_pct": 0.0,
      "avg_delay_min": 0.0,
      "max_delay_min": 0.0,
      "arrivals": []
    },
    {
      "train_name": "RL4",
      "train_type": "Otros",
      "total": 9,
      "delayed": 0,
      "cancelled": 0,
      "delayed_pct": 0.0,
      "avg_delay_min": 0.0,
      "max_delay_min": 0.0,
      "arrivals": []
    },
    {
      "train_name": "RL3",
      "train_type": "Otros",
      "total": 6,
      "delayed": 0,
      "cancelled": 0,
      "delayed_pct": 0.0,
      "avg_delay_min": 0.0,
      "max_delay_min": 0.0,
      "arrivals": []
    },
    {
      "train_name": "R2",
      "train_type": "Otros",
      "total": 52,
      "delayed": 0,
      "cancelled": 0,
      "delayed_pct": 0.0,
      "avg_delay_min": 2.0,
      "max_delay_min": 2.0,
      "arrivals": [
        {
          "train_name": "R2",
          "headsign": "Castelldefels",
          "origin": "Sant Celoni",
          "stop_id": "79011",
          "stop_name": "La Llagosta",
          "scheduled_time": "06:56",
          "estimated_time": "06:58",
          "delay_min": 2.0,
          "status": "en_hora"
        }
      ]
    },
    {
      "train_name": "R2N",
      "train_type": "Otros",
      "total": 73,
      "delayed": 0,
      "cancelled": 0,
      "delayed_pct": 0.0,
      "avg_delay_min": 0.0,
      "max_delay_min": 0.0,
      "arrivals": []
    },
    {
      "train_name": "R1",
      "train_type": "Otros",
      "total": 268,
      "delayed": 0,
      "cancelled": 0,
      "delayed_pct": 0.0,
      "avg_delay_min": 1.4,
      "max_delay_min": 2.0,
      "arrivals": [
        {
          "train_name": "R1",
          "headsign": "Arenys De Mar",
          "origin": "L'hospitalet De Llobregat",
          "stop_id": "79501",
          "stop_name": "Sant Andreu De Llavaneres",
          "scheduled_time": "06:57",
          "estimated_time": "06:59",
          "delay_min": 2.0,
          "status": "en_hora"
        },
        {
          "train_name": "R1",
          "headsign": "L'hospitalet De Llobregat",
          "origin": "Maçanet-Massanes",
          "stop_id": "79605",
          "stop_name": "Malgrat De Mar",
          "scheduled_time": "06:57",
          "estimated_time": "06:59",
          "delay_min": 2.0,
          "status": "en_hora"
        },
        {
          "train_name": "R1",
          "headsign": "L'hospitalet De Llobregat",
          "origin": "Blanes",
          "stop_id": "79501",
          "stop_name": "Sant Andreu De Llavaneres",
          "scheduled_time": "06:56",
          "estimated_time": "06:57",
          "delay_min": 1.0,
          "status": "en_hora"
        },
        {
          "train_name": "R1",
          "headsign": "Blanes",
          "origin": "L'hospitalet De Llobregat",
          "stop_id": "79407",
          "stop_name": "El Masnou",
          "scheduled_time": "06:56",
          "estimated_time": "06:57",
          "delay_min": 1.0,
          "status": "en_hora"
        },
        {
          "train_name": "R1",
          "headsign": "Maçanet-Massanes",
          "origin": "L'hospitalet De Llobregat",
          "stop_id": "79601",
          "stop_name": "Canet De Mar",
          "scheduled_time": "06:57",
          "estimated_time": "06:58",
          "delay_min": 1.0,
          "status": "en_hora"
        }
      ]
    },
    {
      "train_name": "R8",
      "train_type": "Otros",
      "total": 14,
      "delayed": 0,
      "cancelled": 0,
      "delayed_pct": 0.0,
      "avg_delay_min": 0.0,
      "max_delay_min": 0.0,
      "arrivals": []
    },
    {
      "train_name": "R3",
      "train_type": "Otros",
      "total": 125,
      "delayed": 0,
      "cancelled": 0,
      "delayed_pct": 0.0,
      "avg_delay_min": 1.0,
      "max_delay_min": 1.0,
      "arrivals": [
        {
          "train_name": "R3",
          "headsign": "La Garriga",
          "origin": "Ripoll",
          "stop_id": "77113",
          "stop_name": "Sant Quirze De Besora-Montesquiu",
          "scheduled_time": "06:59",
          "estimated_time": "07:00",
          "delay_min": 1.0,
          "status": "en_hora"
        }
      ]
    }
  ]
}