{
  "generated_at": "2026-04-09T17:05:22+02:00",
  "trayectos": [
    {
      "train_type": "Cercanías",
      "headsign": "Madrid-Chamartín-Clara Campoamor",
      "unique_trips": 27,
      "unique_trips_delayed": 1,
      "avg_delay_min": 4.0,
      "max_delay_min": 4.0,
      "arrivals": [
        {
          "train_name": "C8a",
          "origin": "El Escorial",
          "stop_id": "17000",
          "stop_name": "Madrid-Chamartín-Clara Campoamor",
          "scheduled_time": "17:06",
          "estimated_time": "17:10",
          "delay_min": 4.0,
          "status": "retraso_leve"
        }
      ]
    },
    {
      "train_type": "Cercanías",
      "headsign": "Colmenar Viejo",
      "unique_trips": 6,
      "unique_trips_delayed": 1,
      "avg_delay_min": 3.0,
      "max_delay_min": 3.0,
      "arrivals": [
        {
          "train_name": "C4b",
          "origin": "Parla",
          "stop_id": "37001",
          "stop_name": "Madrid-Villaverde Alto",
          "scheduled_time": "17:06",
          "estimated_time": "17:09",
          "delay_min": 3.0,
          "status": "retraso_leve"
        }
      ]
    },
    {
      "train_type": "Cercanías",
      "headsign": "Aranjuez",
      "unique_trips": 5,
      "unique_trips_delayed": 1,
      "avg_delay_min": 2.0,
      "max_delay_min": 2.0,
      "arrivals": [
        {
          "train_name": "C3",
          "origin": "Madrid-Chamartín-Clara Campoamor",
          "stop_id": "60105",
          "stop_name": "Ciempozuelos",
          "scheduled_time": "17:07",
          "estimated_time": "17:09",
          "delay_min": 2.0,
          "status": "retraso_leve"
        }
      ]
    },
    {
      "train_type": "Cercanías",
      "headsign": "Alcobendas-San Sebastián De Los Reyes",
      "unique_trips": 6,
      "unique_trips_delayed": 1,
      "avg_delay_min": 2.0,
      "max_delay_min": 2.0,
      "arrivals": [
        {
          "train_name": "C4a",
          "origin": "Parla",
          "stop_id": "17001",
          "stop_name": "Fuencarral",
          "scheduled_time": "17:08",
          "estimated_time": "17:10",
          "delay_min": 2.0,
          "status": "retraso_leve"
        }
      ]
    },
    {
      "train_type": "Otros",
      "headsign": "Martorell-Central",
      "unique_trips": 5,
      "unique_trips_delayed": 1,
      "avg_delay_min": 0.0,
      "max_delay_min": 0.0,
      "arrivals": []
    }
  ]
}