{
  "generated_at": "2026-04-17T15:10:22+02:00",
  "trayectos": [
    {
      "train_type": "Otros",
      "headsign": "Granollers-Centre",
      "unique_trips": 5,
      "unique_trips_delayed": 1,
      "avg_delay_min": 4.0,
      "max_delay_min": 4.0,
      "arrivals": [
        {
          "train_name": "R2",
          "origin": "Castelldefels",
          "stop_id": "71708",
          "stop_name": "Bellvitge-Gornal",
          "scheduled_time": "15:11",
          "estimated_time": "15:15",
          "delay_min": 4.0,
          "status": "retraso_leve"
        }
      ]
    },
    {
      "train_type": "Cercanías",
      "headsign": "Madrid-Chamartín-Clara Campoamor",
      "unique_trips": 28,
      "unique_trips_delayed": 2,
      "avg_delay_min": 2.0,
      "max_delay_min": 2.0,
      "arrivals": [
        {
          "train_name": "C1",
          "origin": "Madrid-Aeropuerto T4",
          "stop_id": "17000",
          "stop_name": "Madrid-Chamartín-Clara Campoamor",
          "scheduled_time": "15:12",
          "estimated_time": "15:14",
          "delay_min": 2.0,
          "status": "retraso_leve"
        },
        {
          "train_name": "C8b",
          "origin": "Cercedilla",
          "stop_id": "10100",
          "stop_name": "Pinar De Las Rozas",
          "scheduled_time": "15:12",
          "estimated_time": "15:14",
          "delay_min": 2.0,
          "status": "retraso_leve"
        }
      ]
    },
    {
      "train_type": "Cercanías",
      "headsign": "Villalba De Guadarrama",
      "unique_trips": 4,
      "unique_trips_delayed": 1,
      "avg_delay_min": 2.0,
      "max_delay_min": 2.0,
      "arrivals": [
        {
          "train_name": "C10",
          "origin": "Madrid-Chamartín-Clara Campoamor",
          "stop_id": "18001",
          "stop_name": "Madrid-Recoletos",
          "scheduled_time": "15:11",
          "estimated_time": "15:13",
          "delay_min": 2.0,
          "status": "retraso_leve"
        }
      ]
    },
    {
      "train_type": "Cercanías",
      "headsign": "Aranjuez",
      "unique_trips": 8,
      "unique_trips_delayed": 1,
      "avg_delay_min": 2.0,
      "max_delay_min": 2.0,
      "arrivals": [
        {
          "train_name": "C3",
          "origin": "Madrid-Chamartín-Clara Campoamor",
          "stop_id": "60104",
          "stop_name": "Valdemoro",
          "scheduled_time": "15:12",
          "estimated_time": "15:14",
          "delay_min": 2.0,
          "status": "retraso_leve"
        }
      ]
    },
    {
      "train_type": "Cercanías",
      "headsign": "Madrid-Príncipe Pío",
      "unique_trips": 6,
      "unique_trips_delayed": 1,
      "avg_delay_min": 2.0,
      "max_delay_min": 2.0,
      "arrivals": [
        {
          "train_name": "C7",
          "origin": "Guadalajara",
          "stop_id": "70112",
          "stop_name": "Soto Del Henares",
          "scheduled_time": "15:12",
          "estimated_time": "15:14",
          "delay_min": 2.0,
          "status": "retraso_leve"
        }
      ]
    }
  ]
}