{
  "generated_at": "2026-04-10T23:20:13+02:00",
  "trayectos": [
    {
      "train_type": "Cercanías",
      "headsign": "Madrid-Atocha Cercanías",
      "unique_trips": 6,
      "unique_trips_delayed": 1,
      "avg_delay_min": 6.0,
      "max_delay_min": 6.0,
      "arrivals": [
        {
          "train_name": "C7",
          "origin": "Madrid-Príncipe Pío",
          "stop_id": "17000",
          "stop_name": "Madrid-Chamartín-Clara Campoamor",
          "scheduled_time": "23:21",
          "estimated_time": "23:27",
          "delay_min": 6.0,
          "status": "retraso_alto"
        }
      ]
    },
    {
      "train_type": "Otros",
      "headsign": "Reus",
      "unique_trips": 2,
      "unique_trips_delayed": 1,
      "avg_delay_min": 6.0,
      "max_delay_min": 6.0,
      "arrivals": [
        {
          "train_name": "R15",
          "origin": "Sant Vicenç De Calders",
          "stop_id": "71401",
          "stop_name": "Vila-Seca",
          "scheduled_time": "23:22",
          "estimated_time": "23:28",
          "delay_min": 6.0,
          "status": "retraso_alto"
        }
      ]
    },
    {
      "train_type": "Cercanías",
      "headsign": "Cercedilla",
      "unique_trips": 1,
      "unique_trips_delayed": 1,
      "avg_delay_min": 4.0,
      "max_delay_min": 4.0,
      "arrivals": [
        {
          "train_name": "C8b",
          "origin": "Madrid-Chamartín-Clara Campoamor",
          "stop_id": "97201",
          "stop_name": "Madrid-Ramón Y Cajal",
          "scheduled_time": "23:21",
          "estimated_time": "23:25",
          "delay_min": 4.0,
          "status": "retraso_leve"
        }
      ]
    }
  ]
}