{
  "generated_at": "2026-04-18T06:45:24+02:00",
  "trayectos": [
    {
      "train_type": "Cercanías",
      "headsign": "Irun",
      "unique_trips": 4,
      "unique_trips_delayed": 1,
      "avg_delay_min": 4.0,
      "max_delay_min": 4.0,
      "arrivals": [
        {
          "train_name": "C1",
          "origin": "Brinkola",
          "stop_id": "11500",
          "stop_name": "Tolosa",
          "scheduled_time": "06:51",
          "estimated_time": "06:55",
          "delay_min": 4.0,
          "status": "retraso_leve"
        }
      ]
    },
    {
      "train_type": "Cercanías",
      "headsign": "Madrid-Atocha Cercanías",
      "unique_trips": 17,
      "unique_trips_delayed": 2,
      "avg_delay_min": 2.5,
      "max_delay_min": 3.0,
      "arrivals": [
        {
          "train_name": "C5",
          "origin": "Móstoles-El Soto",
          "stop_id": "35609",
          "stop_name": "Embajadores",
          "scheduled_time": "06:47",
          "estimated_time": "06:50",
          "delay_min": 3.0,
          "status": "retraso_leve"
        },
        {
          "train_name": "C5",
          "origin": "Móstoles-El Soto",
          "stop_id": "35610",
          "stop_name": "Las Retamas",
          "scheduled_time": "06:46",
          "estimated_time": "06:48",
          "delay_min": 2.0,
          "status": "retraso_leve"
        }
      ]
    },
    {
      "train_type": "Cercanías",
      "headsign": "Parla",
      "unique_trips": 12,
      "unique_trips_delayed": 1,
      "avg_delay_min": 2.0,
      "max_delay_min": 2.0,
      "arrivals": [
        {
          "train_name": "C4b",
          "origin": "Colmenar Viejo",
          "stop_id": "17003",
          "stop_name": "El Goloso",
          "scheduled_time": "06:46",
          "estimated_time": "06:48",
          "delay_min": 2.0,
          "status": "retraso_leve"
        }
      ]
    },
    {
      "train_type": "Otros",
      "headsign": "Maçanet-Massanes",
      "unique_trips": 2,
      "unique_trips_delayed": 1,
      "avg_delay_min": 2.0,
      "max_delay_min": 2.0,
      "arrivals": [
        {
          "train_name": "R1",
          "origin": "L'hospitalet De Llobregat",
          "stop_id": "79501",
          "stop_name": "Sant Andreu De Llavaneres",
          "scheduled_time": "06:47",
          "estimated_time": "06:49",
          "delay_min": 2.0,
          "status": "retraso_leve"
        }
      ]
    }
  ]
}