{
  "generated_at": "2026-04-14T18:25:18+02:00",
  "trayectos": [
    {
      "train_type": "Cercanías",
      "headsign": "Guadalajara",
      "unique_trips": 9,
      "unique_trips_delayed": 3,
      "avg_delay_min": 2.3,
      "max_delay_min": 3.0,
      "arrivals": [
        {
          "train_name": "C2",
          "origin": "Madrid-Chamartín-Clara Campoamor",
          "stop_id": "70200",
          "stop_name": "Guadalajara",
          "scheduled_time": "18:26",
          "estimated_time": "18:29",
          "delay_min": 3.0,
          "status": "retraso_leve"
        },
        {
          "train_name": "C7",
          "origin": "Madrid-Príncipe Pío",
          "stop_id": "18002",
          "stop_name": "Madrid-Nuevos Ministerios",
          "scheduled_time": "18:26",
          "estimated_time": "18:28",
          "delay_min": 2.0,
          "status": "retraso_leve"
        },
        {
          "train_name": "C2",
          "origin": "Madrid-Chamartín-Clara Campoamor",
          "stop_id": "70002",
          "stop_name": "Asamblea De Madrid-Entrevías",
          "scheduled_time": "18:27",
          "estimated_time": "18:29",
          "delay_min": 2.0,
          "status": "retraso_leve"
        }
      ]
    },
    {
      "train_type": "Cercanías",
      "headsign": "Madrid-Chamartín-Clara Campoamor",
      "unique_trips": 28,
      "unique_trips_delayed": 2,
      "avg_delay_min": 2.5,
      "max_delay_min": 3.0,
      "arrivals": [
        {
          "train_name": "C3",
          "origin": "Aranjuez",
          "stop_id": "60104",
          "stop_name": "Valdemoro",
          "scheduled_time": "18:27",
          "estimated_time": "18:30",
          "delay_min": 3.0,
          "status": "retraso_leve"
        },
        {
          "train_name": "C8a",
          "origin": "El Escorial",
          "stop_id": "10200",
          "stop_name": "Villalba De Guadarrama",
          "scheduled_time": "18:26",
          "estimated_time": "18:28",
          "delay_min": 2.0,
          "status": "retraso_leve"
        }
      ]
    },
    {
      "train_type": "Cercanías",
      "headsign": "Pinar De Las Rozas",
      "unique_trips": 4,
      "unique_trips_delayed": 1,
      "avg_delay_min": 3.0,
      "max_delay_min": 3.0,
      "arrivals": [
        {
          "train_name": "C10",
          "origin": "Madrid-Chamartín-Clara Campoamor",
          "stop_id": "18001",
          "stop_name": "Madrid-Recoletos",
          "scheduled_time": "18:26",
          "estimated_time": "18:29",
          "delay_min": 3.0,
          "status": "retraso_leve"
        }
      ]
    },
    {
      "train_type": "Cercanías",
      "headsign": "Madrid-Príncipe Pío",
      "unique_trips": 6,
      "unique_trips_delayed": 1,
      "avg_delay_min": 2.0,
      "max_delay_min": 2.0,
      "arrivals": [
        {
          "train_name": "C7",
          "origin": "Alcalá De Henares",
          "stop_id": "17000",
          "stop_name": "Madrid-Chamartín-Clara Campoamor",
          "scheduled_time": "18:29",
          "estimated_time": "18:31",
          "delay_min": 2.0,
          "status": "retraso_leve"
        }
      ]
    },
    {
      "train_type": "Cercanías",
      "headsign": "Humanes",
      "unique_trips": 12,
      "unique_trips_delayed": 1,
      "avg_delay_min": 2.0,
      "max_delay_min": 2.0,
      "arrivals": [
        {
          "train_name": "C5",
          "origin": "Móstoles-El Soto",
          "stop_id": "35609",
          "stop_name": "Embajadores",
          "scheduled_time": "18:26",
          "estimated_time": "18:28",
          "delay_min": 2.0,
          "status": "retraso_leve"
        }
      ]
    },
    {
      "train_type": "Cercanías",
      "headsign": "Móstoles-El Soto",
      "unique_trips": 17,
      "unique_trips_delayed": 2,
      "avg_delay_min": 2.0,
      "max_delay_min": 2.0,
      "arrivals": [
        {
          "train_name": "C5",
          "origin": "Fuenlabrada",
          "stop_id": "35604",
          "stop_name": "San José De Valderas",
          "scheduled_time": "18:26",
          "estimated_time": "18:28",
          "delay_min": 2.0,
          "status": "retraso_leve"
        },
        {
          "train_name": "C5",
          "origin": "Humanes",
          "stop_id": "18003",
          "stop_name": "Méndez álvaro P.v.",
          "scheduled_time": "18:26",
          "estimated_time": "18:28",
          "delay_min": 2.0,
          "status": "retraso_leve"
        }
      ]
    },
    {
      "train_type": "Cercanías",
      "headsign": "Fuenlabrada",
      "unique_trips": 6,
      "unique_trips_delayed": 1,
      "avg_delay_min": 2.0,
      "max_delay_min": 2.0,
      "arrivals": [
        {
          "train_name": "C5",
          "origin": "Móstoles-El Soto",
          "stop_id": "35610",
          "stop_name": "Las Retamas",
          "scheduled_time": "18:26",
          "estimated_time": "18:28",
          "delay_min": 2.0,
          "status": "retraso_leve"
        }
      ]
    },
    {
      "train_type": "Cercanías",
      "headsign": "Parla",
      "unique_trips": 12,
      "unique_trips_delayed": 1,
      "avg_delay_min": 2.0,
      "max_delay_min": 2.0,
      "arrivals": [
        {
          "train_name": "C4b",
          "origin": "Colmenar Viejo",
          "stop_id": "37001",
          "stop_name": "Madrid-Villaverde Alto",
          "scheduled_time": "18:26",
          "estimated_time": "18:28",
          "delay_min": 2.0,
          "status": "retraso_leve"
        }
      ]
    },
    {
      "train_type": "Cercanías",
      "headsign": "Málaga-Centro Alameda",
      "unique_trips": 7,
      "unique_trips_delayed": 1,
      "avg_delay_min": 2.0,
      "max_delay_min": 2.0,
      "arrivals": [
        {
          "train_name": "C1",
          "origin": "Fuengirola",
          "stop_id": "54508",
          "stop_name": "La Colina",
          "scheduled_time": "18:26",
          "estimated_time": "18:28",
          "delay_min": 2.0,
          "status": "retraso_leve"
        }
      ]
    },
    {
      "train_type": "Otros",
      "headsign": "Terrassa Estació Del Nord",
      "unique_trips": 13,
      "unique_trips_delayed": 1,
      "avg_delay_min": 0.0,
      "max_delay_min": 0.0,
      "arrivals": []
    },
    {
      "train_type": "Otros",
      "headsign": "Granollers-Centre",
      "unique_trips": 5,
      "unique_trips_delayed": 1,
      "avg_delay_min": 0.0,
      "max_delay_min": 0.0,
      "arrivals": []
    }
  ]
}