{
  "station_id": "05102",
  "name": "San Xoán",
  "generated_at": "2026-04-17T08:45:23+02:00",
  "arrivals": [
    {
      "trip_id": "4604V70003C1",
      "route_id": "46T0001C1",
      "train_name": "C1",
      "train_type": "Cercanías",
      "headsign": "Xuvia",
      "origin": "Ferrol",
      "scheduled_time": "08:58",
      "estimated_time": "08:58",
      "delay_min": 0.0,
      "status": "en_hora"
    },
    {
      "trip_id": "4604V70002C1",
      "route_id": "46T0002C1",
      "train_name": "C1",
      "train_type": "Cercanías",
      "headsign": "Ferrol",
      "origin": "Xuvia",
      "scheduled_time": "09:24",
      "estimated_time": "09:24",
      "delay_min": 0.0,
      "status": "en_hora"
    },
    {
      "trip_id": "4604V70151C1",
      "route_id": "46T0001C1",
      "train_name": "C1",
      "train_type": "Cercanías",
      "headsign": "Ortigueira",
      "origin": "Ferrol",
      "scheduled_time": "09:38",
      "estimated_time": "09:38",
      "delay_min": 0.0,
      "status": "en_hora"
    }
  ]
}