{
  "station_id": "14215",
  "name": "Zurita",
  "generated_at": "2026-04-17T06:45:21+02:00",
  "arrivals": [
    {
      "trip_id": "6204V35903C1",
      "route_id": "62T0002C1",
      "train_name": "C1",
      "train_type": "Cercanías",
      "headsign": "Santander",
      "origin": "Bárcena",
      "scheduled_time": "06:54",
      "estimated_time": "06:54",
      "delay_min": 0.0,
      "status": "en_hora"
    },
    {
      "trip_id": "6204V35905C1",
      "route_id": "62T0002C1",
      "train_name": "C1",
      "train_type": "Cercanías",
      "headsign": "Santander",
      "origin": "Los Corrales De Buelna",
      "scheduled_time": "07:37",
      "estimated_time": "07:37",
      "delay_min": 0.0,
      "status": "en_hora"
    }
  ]
}