{
  "station_id": "79405",
  "name": "Montgat",
  "generated_at": "2026-04-19T14:25:26+02:00",
  "arrivals": [
    {
      "trip_id": "5106D25820R1",
      "route_id": "51T0002R1",
      "train_name": "R1",
      "train_type": "Otros",
      "headsign": "L'hospitalet De Llobregat",
      "origin": "Mataró",
      "scheduled_time": "14:36",
      "estimated_time": "14:36",
      "delay_min": 0.0,
      "status": "en_hora"
    },
    {
      "trip_id": "5106D25821R1",
      "route_id": "51T0001R1",
      "train_name": "R1",
      "train_type": "Otros",
      "headsign": "Mataró",
      "origin": "L'hospitalet De Llobregat",
      "scheduled_time": "14:37",
      "estimated_time": "14:37",
      "delay_min": 0.0,
      "status": "en_hora"
    },
    {
      "trip_id": "5106D25648R1",
      "route_id": "51T0002R1",
      "train_name": "R1",
      "train_type": "Otros",
      "headsign": "L'hospitalet De Llobregat",
      "origin": "Blanes",
      "scheduled_time": "14:51",
      "estimated_time": "14:51",
      "delay_min": 0.0,
      "status": "en_hora"
    },
    {
      "trip_id": "5106D25643R1",
      "route_id": "51T0001R1",
      "train_name": "R1",
      "train_type": "Otros",
      "headsign": "Blanes",
      "origin": "L'hospitalet De Llobregat",
      "scheduled_time": "14:52",
      "estimated_time": "14:52",
      "delay_min": 0.0,
      "status": "en_hora"
    },
    {
      "trip_id": "5106D25822R1",
      "route_id": "51T0002R1",
      "train_name": "R1",
      "train_type": "Otros",
      "headsign": "L'hospitalet De Llobregat",
      "origin": "Mataró",
      "scheduled_time": "15:06",
      "estimated_time": "15:06",
      "delay_min": 0.0,
      "status": "en_hora"
    },
    {
      "trip_id": "5106D25823R1",
      "route_id": "51T0001R1",
      "train_name": "R1",
      "train_type": "Otros",
      "headsign": "Mataró",
      "origin": "L'hospitalet De Llobregat",
      "scheduled_time": "15:07",
      "estimated_time": "15:07",
      "delay_min": 0.0,
      "status": "en_hora"
    },
    {
      "trip_id": "5106D25650R1",
      "route_id": "51T0002R1",
      "train_name": "R1",
      "train_type": "Otros",
      "headsign": "L'hospitalet De Llobregat",
      "origin": "Maçanet-Massanes",
      "scheduled_time": "15:21",
      "estimated_time": "15:21",
      "delay_min": 0.0,
      "status": "en_hora"
    },
    {
      "trip_id": "5106D25647R1",
      "route_id": "51T0001R1",
      "train_name": "R1",
      "train_type": "Otros",
      "headsign": "Maçanet-Massanes",
      "origin": "L'hospitalet De Llobregat",
      "scheduled_time": "15:22",
      "estimated_time": "15:22",
      "delay_min": 0.0,
      "status": "en_hora"
    }
  ]
}