{
  "station_id": "79601",
  "name": "Canet De Mar",
  "generated_at": "2026-04-20T10:00:28+02:00",
  "arrivals": [
    {
      "trip_id": "5107L25632R1",
      "route_id": "51T0002R1",
      "train_name": "R1",
      "train_type": "Otros",
      "headsign": "L'hospitalet De Llobregat",
      "origin": "Blanes",
      "scheduled_time": "10:17",
      "estimated_time": "10:17",
      "delay_min": 0.0,
      "status": "en_hora"
    },
    {
      "trip_id": "5107L25619R1",
      "route_id": "51T0001R1",
      "train_name": "R1",
      "train_type": "Otros",
      "headsign": "Blanes",
      "origin": "L'hospitalet De Llobregat",
      "scheduled_time": "10:27",
      "estimated_time": "10:27",
      "delay_min": 0.0,
      "status": "en_hora"
    },
    {
      "trip_id": "5107L25634R1",
      "route_id": "51T0002R1",
      "train_name": "R1",
      "train_type": "Otros",
      "headsign": "L'hospitalet De Llobregat",
      "origin": "Maçanet-Massanes",
      "scheduled_time": "10:47",
      "estimated_time": "10:47",
      "delay_min": 0.0,
      "status": "en_hora"
    },
    {
      "trip_id": "5107L25621R1",
      "route_id": "51T0001R1",
      "train_name": "R1",
      "train_type": "Otros",
      "headsign": "Maçanet-Massanes",
      "origin": "L'hospitalet De Llobregat",
      "scheduled_time": "10:57",
      "estimated_time": "10:57",
      "delay_min": 0.0,
      "status": "en_hora"
    }
  ]
}