{
  "station_id": "03216",
  "name": "Valencia Joaquin Sorolla",
  "generated_at": "2026-04-11T19:50:03+02:00",
  "arrivals": [
    {
      "trip_id": "0518412026-04-10",
      "route_id": "1700003216LC112",
      "train_name": "AVLO 05184",
      "train_type": "AVLO",
      "headsign": "Valencia Joaquin Sorolla",
      "origin": "Madrid-Chamartín-Clara Campoamor",
      "scheduled_time": "20:34",
      "estimated_time": "20:42",
      "delay_min": 8.0,
      "status": "retraso_leve"
    }
  ]
}