{
  "generated_at": "2026-04-15T11:50:03+02:00",
  "trayectos": [
    {
      "train_type": "AVE",
      "headsign": "Valencia Joaquin Sorolla",
      "unique_trips": 1,
      "unique_trips_delayed": 1,
      "avg_delay_min": 14.0,
      "max_delay_min": 14.0,
      "arrivals": [
        {
          "train_name": "AVE 05100",
          "origin": "Madrid-Chamartín-Clara Campoamor",
          "stop_id": "03213",
          "stop_name": "Requena Utiel",
          "scheduled_time": "12:07",
          "estimated_time": "12:21",
          "delay_min": 14.0,
          "status": "retraso_alto"
        },
        {
          "train_name": "AVE 05100",
          "origin": "Madrid-Chamartín-Clara Campoamor",
          "stop_id": "03216",
          "stop_name": "Valencia Joaquin Sorolla",
          "scheduled_time": "12:34",
          "estimated_time": "12:48",
          "delay_min": 14.0,
          "status": "retraso_alto"
        }
      ]
    },
    {
      "train_type": "Alvia",
      "headsign": "Pamplona/Iruña",
      "unique_trips": 1,
      "unique_trips_delayed": 1,
      "avg_delay_min": 12.0,
      "max_delay_min": 12.0,
      "arrivals": [
        {
          "train_name": "ALVIA 00605",
          "origin": "Madrid Pta.Atocha - Almudena Grandes",
          "stop_id": "70600",
          "stop_name": "Calatayud",
          "scheduled_time": "11:57",
          "estimated_time": "12:09",
          "delay_min": 12.0,
          "status": "retraso_alto"
        }
      ]
    }
  ]
}