{
  "generated_at": "2026-04-14T18:55",
  "insights": [
    {
      "id": "J",
      "text": "Anomalía en trenes Alvia: los retrasos están a 1.8× su media histórica (44% hoy vs 25% habitual). Basado en 1508 registros.",
      "severity": "high",
      "meta": {
        "train_type": "Alvia"
      }
    },
    {
      "id": "J",
      "text": "Anomalía en trenes Media Distancia: los retrasos están a 1.9× su media histórica (28% hoy vs 15% habitual). Basado en 1646 registros.",
      "severity": "high",
      "meta": {
        "train_type": "Media Distancia"
      }
    },
    {
      "id": "J",
      "text": "Anomalía en trenes Otros: los retrasos están a 4.0× su media histórica (30% hoy vs 8% habitual). Basado en 1598 registros.",
      "severity": "high",
      "meta": {
        "train_type": "Otros"
      }
    },
    {
      "id": "J",
      "text": "Anomalía en trenes AVE: los retrasos están a 2.4× su media histórica (35% hoy vs 15% habitual). Basado en 1615 registros.",
      "severity": "high",
      "meta": {
        "train_type": "AVE"
      }
    },
    {
      "id": "J",
      "text": "Anomalía en trenes AVLO: los retrasos están a 2.1× su media histórica (36% hoy vs 17% habitual). Basado en 1486 registros.",
      "severity": "high",
      "meta": {
        "train_type": "AVLO"
      }
    },
    {
      "id": "A",
      "text": "A las 19h se están acumulando los retrasos — 221 trenes afectados",
      "severity": "warn",
      "meta": {
        "hour": 19
      }
    },
    {
      "id": "B",
      "text": "El mayor retraso en este momento es de 97 minutos — tren desde Logroño con parada en Valladolid",
      "severity": "bad",
      "meta": {
        "station_id": "10600",
        "station_name": "Valladolid"
      }
    },
    {
      "id": "C",
      "text": "Linares-Baeza es la estación más afectada ahora mismo: 3 de 4 trenes con retraso",
      "severity": "bad",
      "meta": {
        "station_id": "50300",
        "station_name": "Linares-Baeza"
      }
    },
    {
      "id": "D",
      "text": "Históricamente los miércoles son el día con más retrasos (media 20%); los martes son los más puntuales",
      "severity": "info"
    },
    {
      "id": "E",
      "text": "Hasta las 18:55 hay un 75% más retrasos de lo habitual para un martes (24% vs media histórica 14%)",
      "severity": "bad"
    },
    {
      "id": "F",
      "text": "Entre las 00h y las 11h los retrasos son habitualmente bajos o inexistentes",
      "severity": "ok"
    },
    {
      "id": "G",
      "text": "Esta semana los retrasos están bajando respecto a la anterior (-43% · 6% vs 11%)",
      "severity": "ok"
    },
    {
      "id": "H",
      "text": "La semana del 23/03 fue la peor del último mes con un 22% de trenes con retraso de media",
      "severity": "info"
    }
  ]
}