{
  "generated_at": "2026-04-17T20:15:14+02:00",
  "ccaa": [
    {
      "id": "País Vasco",
      "name": "País Vasco",
      "stations_count": 21,
      "total": 31,
      "delayed": 1,
      "cancelled": 0,
      "avg_delay_min": 31.0,
      "max_delay_min": 31.0,
      "delayed_pct": 0.032,
      "rank_worst": 1,
      "label": "zona_referencia",
      "trend": "stable",
      "narrative": "Referencia de puntualidad: solo el 16.2% de retrasos, de los mejor atendidos del país. Tendencia: estable.",
      "historical_avg_pct": 0.1621,
      "national_avg_pct": 0.2459,
      "n_records": 30
    },
    {
      "id": "Principado de Asturias",
      "name": "Principado de Asturias",
      "stations_count": 30,
      "total": 30,
      "delayed": 18,
      "cancelled": 0,
      "avg_delay_min": 24.7,
      "max_delay_min": 71.0,
      "delayed_pct": 0.6,
      "rank_worst": 2,
      "label": "zona_deterioro",
      "trend": "worsening",
      "narrative": "Situación preocupante: 45.7% de retrasos, por encima de la media (24.6%), con tendencia al alza. Basado en 30 registros.",
      "historical_avg_pct": 0.457,
      "national_avg_pct": 0.2459,
      "n_records": 30
    },
    {
      "id": "Región de Murcia",
      "name": "Región de Murcia",
      "stations_count": 9,
      "total": 19,
      "delayed": 9,
      "cancelled": 0,
      "avg_delay_min": 21.7,
      "max_delay_min": 27.0,
      "delayed_pct": 0.474,
      "rank_worst": 3,
      "label": "zona_deterioro",
      "trend": "worsening",
      "narrative": "Situación preocupante: 31.8% de retrasos, por encima de la media (24.6%), con tendencia al alza. Basado en 30 registros.",
      "historical_avg_pct": 0.3179,
      "national_avg_pct": 0.2459,
      "n_records": 30
    },
    {
      "id": "Comunidad Foral de Navarra",
      "name": "Comunidad Foral de Navarra",
      "stations_count": 13,
      "total": 20,
      "delayed": 5,
      "cancelled": 0,
      "avg_delay_min": 19.4,
      "max_delay_min": 53.0,
      "delayed_pct": 0.25,
      "rank_worst": 4,
      "label": "zona_estable",
      "trend": "improving",
      "narrative": "Servicio normal: 32.1% de retrasos, en línea con la media nacional (24.6%). Tendencia: mejorando.",
      "historical_avg_pct": 0.3207,
      "national_avg_pct": 0.2459,
      "n_records": 30
    },
    {
      "id": "Comunidad Valenciana",
      "name": "Comunidad Valenciana",
      "stations_count": 31,
      "total": 64,
      "delayed": 13,
      "cancelled": 0,
      "avg_delay_min": 16.8,
      "max_delay_min": 36.0,
      "delayed_pct": 0.203,
      "rank_worst": 5,
      "label": "zona_estable",
      "trend": "stable",
      "narrative": "Servicio normal: 20.9% de retrasos, en línea con la media nacional (24.6%). Tendencia: estable.",
      "historical_avg_pct": 0.2092,
      "national_avg_pct": 0.2459,
      "n_records": 30
    },
    {
      "id": "Cataluña",
      "name": "Cataluña",
      "stations_count": 60,
      "total": 147,
      "delayed": 29,
      "cancelled": 0,
      "avg_delay_min": 16.1,
      "max_delay_min": 34.0,
      "delayed_pct": 0.197,
      "rank_worst": 6,
      "label": "zona_referencia",
      "trend": "worsening",
      "narrative": "Referencia de puntualidad: solo el 15.2% de retrasos, de los mejor atendidos del país. Tendencia: empeorando.",
      "historical_avg_pct": 0.1524,
      "national_avg_pct": 0.2459,
      "n_records": 30
    },
    {
      "id": "Andalucía",
      "name": "Andalucía",
      "stations_count": 44,
      "total": 102,
      "delayed": 27,
      "cancelled": 0,
      "avg_delay_min": 16.1,
      "max_delay_min": 28.0,
      "delayed_pct": 0.265,
      "rank_worst": 7,
      "label": "zona_estable",
      "trend": "worsening",
      "narrative": "Servicio normal: 18.4% de retrasos, en línea con la media nacional (24.6%). Tendencia: empeorando.",
      "historical_avg_pct": 0.1835,
      "national_avg_pct": 0.2459,
      "n_records": 30
    },
    {
      "id": "Aragón",
      "name": "Aragón",
      "stations_count": 43,
      "total": 89,
      "delayed": 12,
      "cancelled": 0,
      "avg_delay_min": 16.0,
      "max_delay_min": 19.0,
      "delayed_pct": 0.135,
      "rank_worst": 8,
      "label": "zona_referencia",
      "trend": "worsening",
      "narrative": "Referencia de puntualidad: solo el 10.8% de retrasos, de los mejor atendidos del país. Tendencia: empeorando.",
      "historical_avg_pct": 0.1079,
      "national_avg_pct": 0.2459,
      "n_records": 30
    },
    {
      "id": "Cantabria",
      "name": "Cantabria",
      "stations_count": 7,
      "total": 9,
      "delayed": 2,
      "cancelled": 0,
      "avg_delay_min": 16.0,
      "max_delay_min": 16.0,
      "delayed_pct": 0.222,
      "rank_worst": 9,
      "label": "zona_referencia",
      "trend": "worsening",
      "narrative": "Referencia de puntualidad: solo el 13.5% de retrasos, de los mejor atendidos del país. Tendencia: empeorando.",
      "historical_avg_pct": 0.1349,
      "national_avg_pct": 0.2459,
      "n_records": 30
    },
    {
      "id": "Comunidad de Madrid",
      "name": "Comunidad de Madrid",
      "stations_count": 11,
      "total": 42,
      "delayed": 12,
      "cancelled": 0,
      "avg_delay_min": 14.4,
      "max_delay_min": 23.0,
      "delayed_pct": 0.286,
      "rank_worst": 10,
      "label": "zona_referencia",
      "trend": "worsening",
      "narrative": "Referencia de puntualidad: solo el 16.9% de retrasos, de los mejor atendidos del país. Tendencia: empeorando.",
      "historical_avg_pct": 0.1691,
      "national_avg_pct": 0.2459,
      "n_records": 30
    },
    {
      "id": "Galicia",
      "name": "Galicia",
      "stations_count": 55,
      "total": 82,
      "delayed": 33,
      "cancelled": 0,
      "avg_delay_min": 13.9,
      "max_delay_min": 38.0,
      "delayed_pct": 0.402,
      "rank_worst": 11,
      "label": "zona_deterioro",
      "trend": "worsening",
      "narrative": "Situación preocupante: 30.8% de retrasos, por encima de la media (24.6%), con tendencia al alza. Basado en 30 registros.",
      "historical_avg_pct": 0.3083,
      "national_avg_pct": 0.2459,
      "n_records": 30
    },
    {
      "id": "Castilla-La Mancha",
      "name": "Castilla-La Mancha",
      "stations_count": 26,
      "total": 49,
      "delayed": 21,
      "cancelled": 0,
      "avg_delay_min": 13.8,
      "max_delay_min": 42.0,
      "delayed_pct": 0.429,
      "rank_worst": 12,
      "label": "zona_deterioro",
      "trend": "worsening",
      "narrative": "Situación preocupante: 33.9% de retrasos, por encima de la media (24.6%), con tendencia al alza. Basado en 30 registros.",
      "historical_avg_pct": 0.3388,
      "national_avg_pct": 0.2459,
      "n_records": 30
    },
    {
      "id": "Castilla y León",
      "name": "Castilla y León",
      "stations_count": 54,
      "total": 110,
      "delayed": 34,
      "cancelled": 0,
      "avg_delay_min": 12.7,
      "max_delay_min": 31.0,
      "delayed_pct": 0.309,
      "rank_worst": 13,
      "label": "zona_estable",
      "trend": "worsening",
      "narrative": "Servicio normal: 23.5% de retrasos, en línea con la media nacional (24.6%). Tendencia: empeorando.",
      "historical_avg_pct": 0.2348,
      "national_avg_pct": 0.2459,
      "n_records": 30
    },
    {
      "id": "Extremadura",
      "name": "Extremadura",
      "stations_count": 11,
      "total": 21,
      "delayed": 3,
      "cancelled": 0,
      "avg_delay_min": 11.0,
      "max_delay_min": 12.0,
      "delayed_pct": 0.143,
      "rank_worst": 14,
      "label": "zona_referencia",
      "trend": "stable",
      "narrative": "Referencia de puntualidad: solo el 15.2% de retrasos, de los mejor atendidos del país. Tendencia: estable.",
      "historical_avg_pct": 0.152,
      "national_avg_pct": 0.2459,
      "n_records": 30
    },
    {
      "id": "La Rioja",
      "name": "La Rioja",
      "stations_count": 4,
      "total": 8,
      "delayed": 3,
      "cancelled": 0,
      "avg_delay_min": 11.0,
      "max_delay_min": 11.0,
      "delayed_pct": 0.375,
      "rank_worst": 15,
      "label": "zona_estable",
      "trend": "improving",
      "narrative": "Servicio normal: 44.0% de retrasos, en línea con la media nacional (24.6%). Tendencia: mejorando.",
      "historical_avg_pct": 0.4404,
      "national_avg_pct": 0.2459,
      "n_records": 30
    },
    {
      "id": "Desconocida",
      "name": "Desconocida",
      "stations_count": 6,
      "total": 8,
      "delayed": 0,
      "cancelled": 0,
      "avg_delay_min": 0.0,
      "max_delay_min": 0.0,
      "delayed_pct": 0.0,
      "rank_worst": 16,
      "label": "zona_estable",
      "trend": "stable",
      "narrative": "",
      "historical_avg_pct": 0.0,
      "national_avg_pct": 0.0,
      "n_records": 0
    }
  ],
  "nucleos": [
    {
      "id": "san_sebastian",
      "name": "Núcleo San Sebastián",
      "stations_count": 11,
      "total": 14,
      "delayed": 2,
      "cancelled": 0,
      "avg_delay_min": 33.0,
      "max_delay_min": 53.0,
      "delayed_pct": 0.143,
      "rank_worst": 1
    },
    {
      "id": "bilbao",
      "name": "Núcleo Bilbao",
      "stations_count": 19,
      "total": 34,
      "delayed": 2,
      "cancelled": 0,
      "avg_delay_min": 31.0,
      "max_delay_min": 31.0,
      "delayed_pct": 0.059,
      "rank_worst": 2
    },
    {
      "id": "asturias",
      "name": "Núcleo Asturias",
      "stations_count": 31,
      "total": 31,
      "delayed": 18,
      "cancelled": 0,
      "avg_delay_min": 24.7,
      "max_delay_min": 71.0,
      "delayed_pct": 0.581,
      "rank_worst": 3
    },
    {
      "id": "valencia",
      "name": "Núcleo Valencia",
      "stations_count": 19,
      "total": 38,
      "delayed": 8,
      "cancelled": 0,
      "avg_delay_min": 21.8,
      "max_delay_min": 36.0,
      "delayed_pct": 0.211,
      "rank_worst": 4
    },
    {
      "id": "barcelona",
      "name": "Núcleo Barcelona",
      "stations_count": 26,
      "total": 81,
      "delayed": 13,
      "cancelled": 0,
      "avg_delay_min": 19.4,
      "max_delay_min": 34.0,
      "delayed_pct": 0.16,
      "rank_worst": 5
    },
    {
      "id": "sevilla",
      "name": "Núcleo Sevilla",
      "stations_count": 11,
      "total": 35,
      "delayed": 3,
      "cancelled": 0,
      "avg_delay_min": 19.3,
      "max_delay_min": 25.0,
      "delayed_pct": 0.086,
      "rank_worst": 6
    },
    {
      "id": "murcia",
      "name": "Núcleo Murcia-Alicante",
      "stations_count": 18,
      "total": 40,
      "delayed": 14,
      "cancelled": 0,
      "avg_delay_min": 17.1,
      "max_delay_min": 27.0,
      "delayed_pct": 0.35,
      "rank_worst": 7
    },
    {
      "id": "santander",
      "name": "Núcleo Santander",
      "stations_count": 8,
      "total": 10,
      "delayed": 3,
      "cancelled": 0,
      "avg_delay_min": 16.0,
      "max_delay_min": 16.0,
      "delayed_pct": 0.3,
      "rank_worst": 8
    },
    {
      "id": "zaragoza",
      "name": "Núcleo Zaragoza",
      "stations_count": 38,
      "total": 86,
      "delayed": 13,
      "cancelled": 0,
      "avg_delay_min": 15.5,
      "max_delay_min": 19.0,
      "delayed_pct": 0.151,
      "rank_worst": 9
    },
    {
      "id": "cadiz",
      "name": "Núcleo Cádiz-Málaga",
      "stations_count": 12,
      "total": 19,
      "delayed": 9,
      "cancelled": 0,
      "avg_delay_min": 15.0,
      "max_delay_min": 25.0,
      "delayed_pct": 0.474,
      "rank_worst": 10
    },
    {
      "id": "madrid",
      "name": "Núcleo Madrid",
      "stations_count": 28,
      "total": 69,
      "delayed": 17,
      "cancelled": 0,
      "avg_delay_min": 14.0,
      "max_delay_min": 23.0,
      "delayed_pct": 0.246,
      "rank_worst": 11
    },
    {
      "id": "almeria",
      "name": "Núcleo Almería",
      "stations_count": 2,
      "total": 2,
      "delayed": 0,
      "cancelled": 0,
      "avg_delay_min": 0.0,
      "max_delay_min": 0.0,
      "delayed_pct": 0.0,
      "rank_worst": 12
    }
  ]
}